{
  "$schema": "https://turbo.build/schema.json",
  "globalEnv": [
    
  ],
  "ui": "stream",
  "tasks": {
    "build": {
      "env": [],
      "dependsOn": ["^build"],
      "outputs": [
        ".output",
        "public/registry",
        "public/r",
        ".contentlayer/**",
        ".source/**",
        "!.contentlayer/.cache/**",
        ".next/**",
        "content/docs/openapi/generated/**",
        "!.next/cache/**",
        "dist/**",
        "out",
        "build",
        ".vercel"
      ]
    },
    "lint": {},
    "types:check": {
      "dependsOn": [],
      "outputs": []
    },
    "clean": {
      "cache": false
    },
    "dev": {
      "cache": false,
      "persistent": true
    }
  }
}
